Morelia/__init__.py
Morelia/exceptions.py
Morelia/Commands/PodCommands.py
Morelia/Commands/__init__.py
Morelia/Devices/BasicPodProtocol.py
Morelia/Devices/PodDevice_8206HR.py
Morelia/Devices/PodDevice_8229.py
Morelia/Devices/PodDevice_8274D.py
Morelia/Devices/PodDevice_8401HR.py
Morelia/Devices/PodDevice_8480SC.py
Morelia/Devices/PodDevice_ATD.py
Morelia/Devices/__init__.py
Morelia/Devices/acquisition_device.py
Morelia/Devices/preamp.py
Morelia/Devices/SerialPorts/PortAccess.py
Morelia/Devices/SerialPorts/SerialComm.py
Morelia/Devices/SerialPorts/__init__.py
Morelia/Devices/SerialPorts/queue_manager.py
Morelia/Devices/SerialPorts/queue_server.py
Morelia/Stream/__init__.py
Morelia/Stream/data_flow.py
Morelia/Stream/source.py
Morelia/Stream/sink/Pvfs.h
Morelia/Stream/sink/__init__.py
Morelia/Stream/sink/buffer_sink.py
Morelia/Stream/sink/csv_sink.py
Morelia/Stream/sink/edf_sink.py
Morelia/Stream/sink/influx_sink.py
Morelia/Stream/sink/pvfs.py
Morelia/Stream/sink/quest_sink.py
Morelia/Stream/sink/sink_interface.py
Morelia/Stream/sink/udp_sink.py
Morelia/packet/__init__.py
Morelia/packet/channel_mode.py
Morelia/packet/control_packet.py
Morelia/packet/conversion.py
Morelia/packet/pod_packet.py
Morelia/packet/data/__init__.py
Morelia/packet/data/data_packet.py
Morelia/packet/data/data_packet_8206hr.py
Morelia/packet/data/data_packet_8401hr.py
Morelia/packet/legacy/Binary.py
Morelia/packet/legacy/Packet.py
Morelia/packet/legacy/__init__.py
Morelia/signal/__init__.py
Morelia/signal/digital_signal.py
ptech_morelia-1.8.0.dist-info/licenses/LICENSE.md
pvfs_tools/__init__.py
pvfs_tools/Core/CMakeLists.txt
pvfs_tools/Core/CRC32.py
pvfs_tools/Core/__init__.py
pvfs_tools/Core/indexed_data_file.py
pvfs_tools/Core/libpvfs.so
pvfs_tools/Core/libpvfs_wrapper.so
pvfs_tools/Core/pvfs.cpp
pvfs_tools/Core/pvfs.dll
pvfs_tools/Core/pvfs.h
pvfs_tools/Core/pvfs.lib
pvfs_tools/Core/pvfs_binding.py
pvfs_tools/Core/pvfs_wrapper.cpp
pvfs_tools/Core/pvfs_wrapper.dll
pvfs_tools/Core/pvfs_wrapper.lib
pvfs_tools/Core/video_data_file.py
ptech_morelia-1.8.0.dist-info/METADATA
ptech_morelia-1.8.0.dist-info/WHEEL
ptech_morelia-1.8.0.dist-info/top_level.txt
ptech_morelia-1.8.0.dist-info/RECORD
