Metadata-Version: 2.4
Name: ptech-morelia
Version: 1.8.0
Author: Thresa Kelly, Sree Kondi, James Hurd, Seth Gabbert, Sam Groth, Josselyn T Bui, Andrew Huang
Maintainer: Sam Groth
License: BSD 3-Clause License
Project-URL: repository, https://github.com/Pinnacle-Technology-Inc/Morelia
Requires-Python: >=3.10
License-File: LICENSE.md
Requires-Dist: numpy
Requires-Dist: pandas
Requires-Dist: pyEDFlib
Requires-Dist: pyserial
Requires-Dist: texttable
Requires-Dist: influxdb-client
Requires-Dist: reactivex
Requires-Dist: pydantic
Requires-Dist: SQLAlchemy
Requires-Dist: Pillow>=10.0.0
Requires-Dist: psutil
Provides-Extra: docs
Requires-Dist: sphinx; extra == "docs"
Requires-Dist: autodoc; extra == "docs"
Requires-Dist: sphinx-rtd-theme; extra == "docs"
Requires-Dist: sphinx-autodoc-typehints; extra == "docs"
Provides-Extra: tests
Requires-Dist: pytest; extra == "tests"
Provides-Extra: video
Requires-Dist: av; python_version < "3.11" and extra == "video"
Dynamic: license-file
